pycgdescent-0.10.5.dist-info/RECORD
pycgdescent-0.10.5.dist-info/WHEEL
pycgdescent-0.10.5.dist-info/METADATA
pycgdescent/_cg_descent.pyi
pycgdescent/__init__.py
pycgdescent/_cg_descent.cpython-312-darwin.so
pycgdescent/py.typed
