Metadata-Version: 2.4
Name: pycgdescent
Version: 0.10.5
Summary: Python wrapper for the CG_DESCENT library
Keywords: cg,optimization
Author-Email: Alexandru Fikl <alexfikl@gmail.com>
Maintainer-Email: Alexandru Fikl <alexfikl@gmail.com>
License-Expression: GPL-2.0-or-later AND MIT
Classifier: Development Status :: 3 - Alpha
Classifier: Intended Audience :: Science/Research
Classifier: Programming Language :: Python :: 3 :: Only
Classifier: Programming Language :: Python :: 3.10
Classifier: Programming Language :: Python :: 3.11
Classifier: Programming Language :: Python :: 3.12
Classifier: Programming Language :: Python :: 3.13
Classifier: Programming Language :: Python :: 3.14
Classifier: Topic :: Scientific/Engineering
Classifier: Topic :: Utilities
Project-URL: Documentation, https://pycgdescent.readthedocs.io
Project-URL: Repository, https://github.com/alexfikl/pycgdescent
Requires-Python: >=3.10
Requires-Dist: numpy>=2.1
Requires-Dist: typing-extensions>=4.10
Provides-Extra: dev
Requires-Dist: pyproject-fmt; extra == "dev"
Requires-Dist: reuse; extra == "dev"
Requires-Dist: typos; extra == "dev"
Requires-Dist: uv; extra == "dev"
Provides-Extra: docs
Requires-Dist: sphinx>=6; extra == "docs"
Requires-Dist: sphinx-autoapi; extra == "docs"
Requires-Dist: sphinx-book-theme; extra == "docs"
Provides-Extra: test
Requires-Dist: basedpyright; extra == "test"
Requires-Dist: matplotlib; extra == "test"
Requires-Dist: pytest; extra == "test"
Requires-Dist: rich; extra == "test"
Requires-Dist: ruff; extra == "test"
Requires-Dist: types-dataclasses; extra == "test"
